django_ninja_ts/__init__.py
django_ninja_ts/apps.py
django_ninja_ts/py.typed
django_ninja_ts/management/__init__.py
django_ninja_ts/management/commands/__init__.py
django_ninja_ts/management/commands/generate_ts_client.py
django_ninja_ts/management/commands/runserver.py
django_ninja_ts-2.1.0.dist-info/licenses/LICENSE
django_ninja_ts-2.1.0.dist-info/METADATA
django_ninja_ts-2.1.0.dist-info/WHEEL
django_ninja_ts-2.1.0.dist-info/top_level.txt
django_ninja_ts-2.1.0.dist-info/RECORD
