Metadata-Version: 2.4
Name: django-ninja-ts
Version: 2.1.0
Summary: Auto-generate TypeScript clients for Django Ninja during runserver
Author: Django Ninja TS Contributors
License: MIT
Project-URL: Homepage, https://github.com/fa-krug/django-ninja-ts
Project-URL: Repository, https://github.com/fa-krug/django-ninja-ts
Project-URL: Issues, https://github.com/fa-krug/django-ninja-ts/issues
Keywords: django,ninja,typescript,openapi,codegen
Classifier: Development Status :: 4 - Beta
Classifier: Environment :: Web Environment
Classifier: Framework :: Django
Classifier: Framework :: Django :: 4.0
Classifier: Framework :: Django :: 4.1
Classifier: Framework :: Django :: 4.2
Classifier: Framework :: Django :: 5.0
Classifier: Intended Audience :: Developers
Classifier: License :: OSI Approved :: MIT License
Classifier: Operating System :: OS Independent
Classifier: Programming Language :: Python :: 3
Classifier: Programming Language :: Python :: 3.8
Classifier: Programming Language :: Python :: 3.9
Classifier: Programming Language :: Python :: 3.10
Classifier: Programming Language :: Python :: 3.11
Classifier: Programming Language :: Python :: 3.12
Classifier: Topic :: Internet :: WWW/HTTP
Classifier: Topic :: Software Development :: Code Generators
Classifier: Typing :: Typed
Requires-Python: >=3.8
License-File: LICENSE
Requires-Dist: Django>=4.0
Requires-Dist: django-ninja>=1.0
Requires-Dist: openapi-ts-client>=1.4.0
Provides-Extra: dev
Requires-Dist: pytest>=7.0; extra == "dev"
Requires-Dist: pytest-django>=4.5; extra == "dev"
Requires-Dist: pytest-mock>=3.10; extra == "dev"
Requires-Dist: ruff>=0.4.0; extra == "dev"
Requires-Dist: pre-commit>=3.0; extra == "dev"
Dynamic: license-file
